Workbook

Sheet 0 Cover
A1: PayPal Capital Allocation Review
A2: Objective | B2: Should PayPal prioritize share repurchases, debt reduction, a strategic acquisition, or greater investment in Venmo and branded checkout?
A3: Recommendation | B3: Prioritize Venmo + branded checkout investment, continue valuation-sensitive buybacks, selectively reduce debt, avoid large M&A.
A4: DCF implied share price | B4: ='4 DCF'!B22 -> 93.908819
A5: Current share price | B5: ='1 Inputs'!B3 -> 56.07
A6: 2026E repurchase program | B6: ='1 Inputs'!B18 -> 6000
A7: Scenario | B7: Base case; update assumptions in Inputs tab
A8: Resources | B8: Company 10-K, 1Q26 earnings release and presentation, market data, transaction announcements
A9: Main conclusion | B9: PayPal's capital allocation should solve the growth and multiple problem first; buybacks are second-best while valuation remains discounted.
A10: Model units | B10: $mm except per-share, % and multiples

Sheet 1 Inputs
A1: Inputs and Assumptions
A2: Market / Balance Sheet | B2: Value | C2: Units | D2: Source
A3: Current share price | B3: 56.07 | C3: $/sh | D3: web finance snapshot
A4: Diluted shares | B4: 920 | C4: mm | D4: market cap / price; model input
A5: Market capitalization | B5: 51584 | C5: $mm | D5: web finance snapshot
A6: Cash + investments | B6: 13500 | C6: $mm | D6: PayPal 1Q26 earnings release
A7: Debt | B7: 11600 | C7: $mm | D7: PayPal 1Q26 earnings release
A8: Net debt / (cash) | B8: =B7-B6 -> -1900 | C8: $mm | D8: formula
A9: WACC | B9: 0.0925 | C9: % | D9: model assumption
A10: Terminal growth | B10: 0.025 | C10: % | D10: model assumption
A11: Cost of debt | B11: 0.0525 | C11: % | D11: model assumption
A12: Tax rate | B12: 0.205 | C12: % | D12: PayPal / model assumption
A13: Minimum cash | B13: 6000 | C13: $mm | D13: model assumption
A14: Acquisition price | B14: 3000 | C14: $mm | D14: illustrative tuck-in acquisition
A15: Target revenue | B15: 800 | C15: $mm | D15: illustrative target
A16: Target EBITDA margin | B16: 0.25 | C16: % | D16: illustrative target
A17: Cost synergies | B17: 75 | C17: $mm | D17: illustrative synergy estimate
A18: 2026E share repurchases | B18: 6000 | C18: $mm | D18: PayPal FY2026 guidance / model
A19: Venmo + checkout investment | B19: 1000 | C19: $mm | D19: strategic reinvestment case
A22: Forecast Assumptions | B22: 2026E | C22: 2027E | D22: 2028E | E22: 2029E | F22: 2030E
A23: Revenue growth | B23: 0.05 | C23: 0.055 | D23: 0.06 | E23: 0.055 | F23: 0.05
A24: Operating margin | B24: 0.182 | C24: 0.185 | D24: 0.19 | E24: 0.195 | F24: 0.2
A25: D&A / revenue | B25: 0.029 | C25: 0.028 | D25: 0.028 | E25: 0.027 | F25: 0.027
A26: Capex / revenue | B26: 0.03 | C26: 0.03 | D26: 0.03 | E26: 0.03 | F26: 0.03
A27: Change in NWC / revenue | B27: 0.005 | C27: 0.006 | D27: 0.006 | E27: 0.006 | F27: 0.006
A28: Share repurchases | B28: 6000 | C28: 4500 | D28: 4000 | E28: 3500 | F28: 3000
A29: Dividend / share | B29: 0.56 | C29: 0.58 | D29: 0.6 | E29: 0.63 | F29: 0.66

Sheet 2 Historical FS
A1: Historical Financial Statement Analysis
A3: Income Statement | B3: 2021A | C3: 2022A | D3: 2023A | E3: 2024A | F3: 2025A
A4: Revenue | B4: 25371 | C4: 27518 | D4: 29771 | E4: 31797 | F4: 33172
A5: Revenue growth | C5: 0.085 | D5: 0.082 | E5: 0.068 | F5: 0.043
A6: Operating income | B6: 4262 | C6: 3837 | D6: 5028 | E6: 5325 | F6: 6065
A7: Operating margin | B7: 0.168 | C7: 0.139 | D7: 0.169 | E7: 0.167 | F7: 0.183
A8: Net income | B8: 4169 | C8: 2419 | D8: 4246 | E8: 4147 | F8: 5233
A9: Diluted EPS | B9: 3.52 | C9: 2.09 | D9: 3.84 | E9: 3.99 | F9: 5.41
A10: Diluted shares | B10: 1185 | C10: 1157 | D10: 1107 | E10: 1039 | F10: 968
A12: Cash Flow / Drivers | B12: 2021A | C12: 2022A | D12: 2023A | E12: 2024A | F12: 2025A / 1Q26
A13: CFO | B13: 5797 | C13: 5813 | D13: 4843 | E13: 7450 | F13: 6416
A14: Capex | B14: -908 | C14: -706 | D14: -623 | E14: -683 | F14: -852
A15: Free cash flow | B15: 4889 | C15: 5107 | D15: 4220 | E15: 6767 | F15: 5564
A16: Share repurchases | D16: 5002 | E16: 6047 | F16: 6052
A17: TPV ($bn) | E17: 1675 | F17: 1790
A18: Active accounts (mm) | E18: 434 | F18: 439
A19: 1Q26 TPV ($bn) | F19: 464
A20: 1Q26 branded checkout TPV growth FXN | F20: 0.02
A21: 1Q26 Venmo TPV growth FXN | F21: 0.14

Sheet 3 Forecast
A1: Three-Statement Forecast
A3: Income Statement | B3: 2025A | C3: 2026E | D3: 2027E | E3: 2028E | F3: 2029E | G3: 2030E
A4: Revenue | B4: 33172 | C4: =B4*(1+'1 Inputs'!B23) -> 34830.6 | D4: =C4*(1+'1 Inputs'!C23) -> 36746.283 | E4: =D4*(1+'1 Inputs'!D23) -> 38951.06 | F4: =E4*(1+'1 Inputs'!E23) -> 41093.368 | G4: =F4*(1+'1 Inputs'!F23) -> 43148.037
A5: Revenue growth | B5: 0.043 | C5: =C4/B4-1 -> 0.05 | D5: =D4/C4-1 -> 0.055 | E5: =E4/D4-1 -> 0.06 | F5: =F4/E4-1 -> 0.055 | G5: =G4/F4-1 -> 0.05
A6: Operating income | B6: 6065 | C6: =C4*'1 Inputs'!B24 -> 6339.1692 | D6: =D4*'1 Inputs'!C24 -> 6798.0624 | E6: =E4*'1 Inputs'!D24 -> 7400.7014 | F6: =F4*'1 Inputs'!E24 -> 8013.2068 | G6: =G4*'1 Inputs'!F24 -> 8629.6073
A7: Operating margin | B7: 0.183 | C7: =C6/C4 -> 0.182 | D7: =D6/D4 -> 0.185 | E7: =E6/E4 -> 0.19 | F7: =F6/F4 -> 0.195 | G7: =G6/G4 -> 0.2
A8: Interest expense | B8: 0 | C8: =-C28*'1 Inputs'!$B$11 -> -1063.44 | D8: =-D28*'1 Inputs'!$B$11 -> -1063.44 | E8: =-E28*'1 Inputs'!$B$11 -> -1063.44 | F8: =-F28*'1 Inputs'!$B$11 -> -1063.44 | G8: =-G28*'1 Inputs'!$B$11 -> -1063.44
A9: Pre-tax income | B9: 6292 | C9: =C6+C8 -> 5275.7292 | D9: =D6+D8 -> 5734.6224 | E9: =E6+E8 -> 6337.2614 | F9: =F6+F8 -> 6949.7668 | G9: =G6+G8 -> 7566.1673
A10: Tax expense | B10: -1059 | C10: =-C9*'1 Inputs'!$B$12 -> -1081.5245 | D10: =-D9*'1 Inputs'!$B$12 -> -1175.5976 | E10: =-E9*'1 Inputs'!$B$12 -> -1299.1386 | F10: =-F9*'1 Inputs'!$B$12 -> -1424.7022 | G10: =-G9*'1 Inputs'!$B$12 -> -1551.0643
A11: Net income | B11: 5233 | C11: =C9+C10 -> 4194.2047 | D11: =D9+D10 -> 4559.0248 | E11: =E9+E10 -> 5038.1228 | F11: =F9+F10 -> 5525.0646 | G11: =G9+G10 -> 6015.103
A12: Diluted shares | B12: 968 | C12: =MAX(0,B12-('1 Inputs'!B28/'1 Inputs'!$B$3)) -> 860.9909 | D12: =MAX(0,C12-('1 Inputs'!C28/'1 Inputs'!$B$3)) -> 780.73408 | E12: =MAX(0,D12-('1 Inputs'!D28/'1 Inputs'!$B$3)) -> 709.39469 | F12: =MAX(0,E12-('1 Inputs'!E28/'1 Inputs'!$B$3)) -> 646.97271 | G12: =MAX(0,F12-('1 Inputs'!F28/'1 Inputs'!$B$3)) -> 593.46816
A13: Diluted EPS | B13: 5.41 | C13: =C11/C12 -> 4.8713694 | D13: =D11/D12 -> 5.8394079 | E13: =E11/E12 -> 7.1020025 | F13: =F11/F12 -> 8.5398727 | G13: =G11/G12 -> 10.135511
A16: Cash Flow & Balance Sheet | B16: 2025A | C16: 2026E | D16: 2027E | E16: 2028E | F16: 2029E | G16: 2030E
A17: Net income | B17: 5233 | C17: =C11 -> 4194.2047 | D17: =D11 -> 4559.0248 | E17: =E11 -> 5038.1228 | F17: =F11 -> 5525.0646 | G17: =G11 -> 6015.103
A18: D&A | B18: 963 | C18: =C4*'1 Inputs'!B25 -> 1010.0874 | D18: =D4*'1 Inputs'!C25 -> 1028.8959 | E18: =E4*'1 Inputs'!D25 -> 1090.6297 | F18: =F4*'1 Inputs'!E25 -> 1109.5209 | G18: =G4*'1 Inputs'!F25 -> 1164.997
A19: Change in NWC | B19: -200 | C19: =-C4*'1 Inputs'!B27 -> -174.153 | D19: =-D4*'1 Inputs'!C27 -> -220.4777 | E19: =-E4*'1 Inputs'!D27 -> -233.70636 | F19: =-F4*'1 Inputs'!E27 -> -246.56021 | G19: =-G4*'1 Inputs'!F27 -> -258.88822
A20: Capex | B20: -852 | C20: =-C4*'1 Inputs'!B26 -> -1044.918 | D20: =-D4*'1 Inputs'!C26 -> -1102.3885 | E20: =-E4*'1 Inputs'!D26 -> -1168.5318 | F20: =-F4*'1 Inputs'!E26 -> -1232.801 | G20: =-G4*'1 Inputs'!F26 -> -1294.4411
A21: Free cash flow | B21: 5564 | C21: =SUM(C17:C20) -> 3985.2211 | D21: =SUM(D17:D20) -> 4265.0545 | E21: =SUM(E17:E20) -> 4726.5143 | F21: =SUM(F17:F20) -> 5155.2243 | G21: =SUM(G17:G20) -> 5626.7707
A22: Share repurchases | B22: -6052 | C22: =-'1 Inputs'!B28 -> -6000 | D22: =-'1 Inputs'!C28 -> -4500 | E22: =-'1 Inputs'!D28 -> -4000 | F22: =-'1 Inputs'!E28 -> -3500 | G22: =-'1 Inputs'!F28 -> -3000
A23: Dividends | B23: -130 | C23: =-B12*'1 Inputs'!B29 -> -542.08 | D23: =-C12*'1 Inputs'!C29 -> -499.37472 | E23: =-D12*'1 Inputs'!D29 -> -468.44045 | F23: =-E12*'1 Inputs'!E29 -> -446.91865 | G23: =-F12*'1 Inputs'!F29 -> -427.00199
A24: Ending cash | B24: 12848 | C24: =MAX('1 Inputs'!$B$13,B24+C21+C22+C23) -> 10291.141 | D24: =MAX('1 Inputs'!$B$13,C24+D21+D22+D23) -> 9556.8209 | E24: =MAX('1 Inputs'!$B$13,D24+E21+E22+E23) -> 9814.8948 | F24: =MAX('1 Inputs'!$B$13,E24+F21+F22+F23) -> 11023.2 | G24: =MAX('1 Inputs'!$B$13,F24+G21+G22+G23) -> 13222.969
A25: PP&E | B25: 2310 | C25: =B25-(C20)-C18 -> 2344.8306 | D25: =C25-(D20)-D18 -> 2418.3232 | E25: =D25-(E20)-E18 -> 2496.2253 | F25: =E25-(F20)-F18 -> 2619.5054 | G25: =F25-(G20)-G18 -> 2748.9495
A26: Total assets | B26: 80173 | C26: =B26+(C24-B24)+(C25-B25) -> 77650.972 | D26: =C26+(D24-C24)+(D25-C25) -> 76990.144 | E26: =D26+(E24-D24)+(E25-D25) -> 77326.12 | F26: =E26+(F24-E24)+(F25-E25) -> 78657.706 | G26: =F26+(G24-F24)+(G25-F25) -> 80986.919
A27: Debt | B27: 9987 | C27: =B27+C11+C22+C23 -> 7639.1247 | D27: =C27+D11+D22+D23 -> 7198.7748 | E27: =D27+E11+E22+E23 -> 7768.4571 | F27: =E27+F11+F22+F23 -> 9346.6031 | G27: =F27+G11+G22+G23 -> 11934.704
A28: Equity | B28: 20256 | C28: =B28 -> 20256 | D28: =C28 -> 20256 | E28: =D28 -> 20256 | F28: =E28 -> 20256 | G28: =F28 -> 20256
A29: Debt / EBITDA | B29: 1.42 | C29: =C28/(C6+C18) -> 2.7561971 | D29: =D28/(D6+D18) -> 2.5879785 | E29: =E28/(E6+E18) -> 2.3854917 | F29: =F28/(F6+F18) -> 2.2203885 | G29: =G28/(G6+G18) -> 2.0680774
A30: Interest coverage | B30: 0 | C30: =IFERROR(C6/ABS(C8),0) -> 5.9610032 | D30: =IFERROR(D6/ABS(D8),0) -> 6.3925208 | E30: =IFERROR(E6/ABS(E8),0) -> 6.9592092 | F30: =IFERROR(F6/ABS(F8),0) -> 7.5351753 | G30: =IFERROR(G6/ABS(G8),0) -> 8.1148042
A31: Net debt / EBITDA | B31: -0.41 | C31: =(C28-C24)/(C6+C18) -> 1.3559003 | D31: =(D28-D24)/(D6+D18) -> 1.3669651 | E31: =(E28-E24)/(E6+E18) -> 1.2296194 | F31: =(F28-F24)/(F6+F18) -> 1.0120657 | G31: =(G28-G24)/(G6+G18) -> 0.71805155
A32: Adjusted FCF conversion | B32: 1.06 | C32: =C21/C11 -> 0.95017325 | D32: =D21/D11 -> 0.93551905 | E32: =E21/E11 -> 0.93814988 | F32: =F21/F11 -> 0.93306136 | G32: =G21/G11 -> 0.93544045

Sheet 4 DCF
A1: DCF Valuation
A3: UFCF Build | B3: 2026E | C3: 2027E | D3: 2028E | E3: 2029E | F3: 2030E
A4: EBIT | B4: ='3 Forecast'!C6 -> 6339.1692 | C4: ='3 Forecast'!D6 -> 6798.0624 | D4: ='3 Forecast'!E6 -> 7400.7014 | E4: ='3 Forecast'!F6 -> 8013.2068 | F4: ='3 Forecast'!G6 -> 8629.6073
A5: Tax on EBIT | B5: =-B4*'1 Inputs'!$B$12 -> -1299.5297 | C5: =-C4*'1 Inputs'!$B$12 -> -1393.6028 | D5: =-D4*'1 Inputs'!$B$12 -> -1517.1438 | E5: =-E4*'1 Inputs'!$B$12 -> -1642.7074 | F5: =-F4*'1 Inputs'!$B$12 -> -1769.0695
A6: NOPAT | B6: =B4+B5 -> 5039.6395 | C6: =C4+C5 -> 5404.4596 | D6: =D4+D5 -> 5883.5576 | E6: =E4+E5 -> 6370.4994 | F6: =F4+F5 -> 6860.5378
A7: D&A | B7: ='3 Forecast'!C18 -> 1010.0874 | C7: ='3 Forecast'!D18 -> 1028.8959 | D7: ='3 Forecast'!E18 -> 1090.6297 | E7: ='3 Forecast'!F18 -> 1109.5209 | F7: ='3 Forecast'!G18 -> 1164.997
A8: Change in NWC | B8: ='3 Forecast'!C19 -> -174.153 | C8: ='3 Forecast'!D19 -> -220.4777 | D8: ='3 Forecast'!E19 -> -233.70636 | E8: ='3 Forecast'!F19 -> -246.56021 | F8: ='3 Forecast'!G19 -> -258.88822
A9: Capex | B9: ='3 Forecast'!C20 -> -1044.918 | C9: ='3 Forecast'!D20 -> -1102.3885 | D9: ='3 Forecast'!E20 -> -1168.5318 | E9: ='3 Forecast'!F20 -> -1232.801 | F9: ='3 Forecast'!G20 -> -1294.4411
A10: UFCF | B10: =SUM(B6:B9) -> 4830.6559 | C10: =SUM(C6:C9) -> 5110.4893 | D10: =SUM(D6:D9) -> 5571.9491 | E10: =SUM(E6:E9) -> 6000.6591 | F10: =SUM(F6:F9) -> 6472.2055
A11: Discount factor | B11: =1/(1+'1 Inputs'!$B$9)^1 -> 0.91533181 | C11: =1/(1+'1 Inputs'!$B$9)^2 -> 0.83783232 | D11: =1/(1+'1 Inputs'!$B$9)^3 -> 0.76689457 | E11: =1/(1+'1 Inputs'!$B$9)^4 -> 0.70196299 | F11: =1/(1+'1 Inputs'!$B$9)^5 -> 0.64252906
A12: PV of UFCF | B12: =B10*B11 -> 4421.653 | C12: =C10*C11 -> 4281.7331 | D12: =D10*D11 -> 4273.0975 | E12: =E10*E11 -> 4212.2406 | F12: =F10*F11 -> 4158.5801
A14: Valuation Output | B14: Value
A15: PV explicit UFCF | B15: =SUM(B12:F12) -> 21347.304
A16: Terminal value | B16: =F10*(1+'1 Inputs'!$B$10)/('1 Inputs'!$B$9-'1 Inputs'!$B$10) -> 98281.639
A17: PV terminal value | B17: =B16*F11 -> 63148.809
A18: Enterprise value | B18: =B15+B17 -> 84496.113
A19: Net debt / (cash) | B19: ='1 Inputs'!B7-'1 Inputs'!B6 -> -1900
A20: Equity value | B20: =B18-B19 -> 86396.113
A21: Diluted shares | B21: ='1 Inputs'!B4 -> 920
A22: Implied share price | B22: =B20/B21 -> 93.908819
A25: Sensitivity: Implied Share Price | B25: 8.0% | C25: 8.5% | D25: 9.0% | E25: 9.5% | F25: 10.0%
A26: 0.015 | B26: =(SUM(B12:F12)+(F10*(1+A26)/(0.08-A26))*F11-B19)/B21 -> 95.853404 | C26: =(SUM(B12:F12)+(F10*(1+A26)/(0.085-A26))*F11-B19)/B21 -> 90.811648 | D26: =(SUM(B12:F12)+(F10*(1+A26)/(0.09-A26))*F11-B19)/B21 -> 86.442125 | E26: =(SUM(B12:F12)+(F10*(1+A26)/(0.095-A26))*F11-B19)/B21 -> 82.618793 | F26: =(SUM(B12:F12)+(F10*(1+A26)/(0.1-A26))*F11-B19)/B21 -> 79.245264
A27: 0.02 | B27: =(SUM(B12:F12)+(F10*(1+A27)/(0.08-A27))*F11-B19)/B21 -> 102.11214 | C27: =(SUM(B12:F12)+(F10*(1+A27)/(0.085-A27))*F11-B19)/B21 -> 96.201112 | D27: =(SUM(B12:F12)+(F10*(1+A27)/(0.09-A27))*F11-B19)/B21 -> 91.134519 | E27: =(SUM(B12:F12)+(F10*(1+A27)/(0.095-A27))*F11-B19)/B21 -> 86.743471 | F27: =(SUM(B12:F12)+(F10*(1+A27)/(0.1-A27))*F11-B19)/B21 -> 82.901305
A28: 0.025 | B28: =(SUM(B12:F12)+(F10*(1+A28)/(0.08-A28))*F11-B19)/B21 -> 109.50882 | C28: =(SUM(B12:F12)+(F10*(1+A28)/(0.085-A28))*F11-B19)/B21 -> 102.48882 | D28: =(SUM(B12:F12)+(F10*(1+A28)/(0.09-A28))*F11-B19)/B21 -> 96.548819 | E28: =(SUM(B12:F12)+(F10*(1+A28)/(0.095-A28))*F11-B19)/B21 -> 91.45739 | F28: =(SUM(B12:F12)+(F10*(1+A28)/(0.1-A28))*F11-B19)/B21 -> 87.044818
A29: 0.03 | B29: =(SUM(B12:F12)+(F10*(1+A29)/(0.08-A29))*F11-B19)/B21 -> 118.38484 | C29: =(SUM(B12:F12)+(F10*(1+A29)/(0.085-A29))*F11-B19)/B21 -> 109.91975 | D29: =(SUM(B12:F12)+(F10*(1+A29)/(0.09-A29))*F11-B19)/B21 -> 102.8655 | E29: =(SUM(B12:F12)+(F10*(1+A29)/(0.095-A29))*F11-B19)/B21 -> 96.896526 | F29: =(SUM(B12:F12)+(F10*(1+A29)/(0.1-A29))*F11-B19)/B21 -> 91.780261
A30: 0.035 | B30: =(SUM(B12:F12)+(F10*(1+A30)/(0.08-A30))*F11-B19)/B21 -> 129.23331 | C30: =(SUM(B12:F12)+(F10*(1+A30)/(0.085-A30))*F11-B19)/B21 -> 118.83686 | D30: =(SUM(B12:F12)+(F10*(1+A30)/(0.09-A30))*F11-B19)/B21 -> 110.33067 | E30: =(SUM(B12:F12)+(F10*(1+A30)/(0.095-A30))*F11-B19)/B21 -> 103.24219 | F30: =(SUM(B12:F12)+(F10*(1+A30)/(0.1-A30))*F11-B19)/B21 -> 97.244234

Sheet 5 Trading Comps
A1: Trading Comparables
A3: Company | B3: Ticker | C3: Market Cap | D3: Enterprise Value | E3: Revenue | F3: EBITDA | G3: EV / Revenue | H3: EV / EBITDA
A4: PayPal | B4: PYPL | C4: 51584 | D4: 49600 | E4: 33500 | F4: 7500 | G4: =D4/E4 -> 1.480597 | H4: =D4/F4 -> 6.6133333
A5: Block | B5: XYZ | C5: 45000 | D5: 43000 | E5: 27000 | F5: 5050 | G5: =D5/E5 -> 1.5925926 | H5: =D5/F5 -> 8.5148515
A6: Adyen | B6: ADYEN | C6: 29000 | D6: 17000 | E6: 3036 | F6: 1604 | G6: =D6/E6 -> 5.599473 | H6: =D6/F6 -> 10.598504
A7: Fiserv | B7: FI | C7: 27200 | D7: 55700 | E7: 20600 | F7: 8490 | G7: =D7/E7 -> 2.7038835 | H7: =D7/F7 -> 6.5606596
A8: FIS | B8: FIS | C8: 35000 | D8: 48000 | E8: 13600 | F8: 5330 | G8: =D8/E8 -> 3.5294118 | H8: =D8/F8 -> 9.0056285
A9: Global Payments | B9: GPN | C9: 22100 | D9: 22100 | E9: 12200 | F9: 4910 | G9: =D9/E9 -> 1.8114754 | H9: =D9/F9 -> 4.5010183
A10: Median | C10: =MEDIAN(C4:C9) -> 32000 | D10: =MEDIAN(D4:D9) -> 45500 | E10: =MEDIAN(E4:E9) -> 17100 | F10: =MEDIAN(F4:F9) -> 5190 | G10: =MEDIAN(G4:G9) -> 2.2576795 | H10: =MEDIAN(H4:H9) -> 7.5640924
A11: Implied PYPL EV @ median revenue | E11: ='3 Forecast'!C4 -> 34830.6 | G11: =G10 -> 2.2576795 | H11: ='3 Forecast'!C4*G10 -> 78636.33
A12: Implied PYPL EV @ median EBITDA | E12: ='3 Forecast'!C6+'3 Forecast'!C18 -> 7349.2566 | G12: =H10 -> 7.5640924 | H12: =('3 Forecast'!C6+'3 Forecast'!C18)*H10 -> 55590.456

Sheet 6 Precedents
A1: Precedent Transactions
A3: Year | B3: Acquiror | C3: Target | D3: Value | E3: Consideration | F3: Rationale | G3: EV/Rev | H3: EV/EBITDA
A4: 2020 | B4: PayPal | C4: Honey | D4: 4000 | E4: Cash | F4: Shopping rewards / checkout engagement
A5: 2022 | B5: Block | C5: Afterpay | D5: 29000 | E5: Stock | F5: BNPL / consumer commerce
A6: 2024 | B6: Visa | C6: Pismo | D6: 1000 | E6: Cash | F6: Issuer processing / banking infrastructure
A7: 2019 | B7: Fiserv | C7: First Data | D7: 22000 | E7: Stock | F7: Merchant acquiring scale | H7: 10
A8: 2019 | B8: Global Payments | C8: TSYS | D8: 21500 | E8: Stock | F8: Issuer processing + acquiring scale | H8: 12
A9: 2020 | B9: Worldline | C9: Ingenico | D9: 8600 | E9: Cash/stock | F9: Merchant acquiring consolidation | H9: 9
A10: Median | D10: =MEDIAN(D4:D9) -> 15050 | H10: =MEDIAN(H7:H9) -> 10
A12: Takeaway | B12: Large payment acquisitions carry strategic value but meaningful premium/integration risk.
A13: Implication | B13: Limit M&A to disciplined tuck-ins that accelerate checkout, risk, identity, rewards, or Venmo monetization.

Sheet 7 Financing Alternatives
A1: Financing / Acquisition Alternatives
A3: Alternative | B3: 2026E Size | C3: Funding | D3: Pro Forma Debt | E3: Net Debt/EBITDA | F3: Interest Coverage | G3: EPS Impact | H3: Recommendation
A4: Share repurchases | B4: ='1 Inputs'!B18 -> 6000 | C4: FCF + cash | D4: ='3 Forecast'!C28 -> 20256 | E4: ='3 Forecast'!C31 -> 1.3559003 | F4: ='3 Forecast'!C30 -> 5.9610032 | G4: Accretive if below intrinsic value | H4: Do, valuation-sensitive
A5: Debt reduction | B5: 1500 | C5: cash / FCF | D5: ='3 Forecast'!C28-B5 -> 18756 | E5: =(D5-'3 Forecast'!C24)/('3 Forecast'!C6+'3 Forecast'!C18) -> 1.151798 | F5: =IFERROR('3 Forecast'!C6/(ABS('3 Forecast'!C8)-B5*'1 Inputs'!$B$11),0) -> 6.4377309 | G5: Small dilution from fewer buybacks | H5: Selective
A6: Strategic acquisition | B6: ='1 Inputs'!B14 -> 3000 | C6: 50% cash / 50% debt | D6: ='3 Forecast'!C28+0.5*B6 -> 21756 | E6: =(D6-'3 Forecast'!C24)/('3 Forecast'!C6+'3 Forecast'!C18+'1 Inputs'!B15*'1 Inputs'!B16) -> 1.5186739 | F6: =IFERROR('3 Forecast'!C6/(ABS('3 Forecast'!C8)+0.5*B6*'1 Inputs'!$B$11),0) -> 5.5500129 | G6: Target-dependent | H6: Tuck-ins only
A7: Venmo + checkout investment | B7: ='1 Inputs'!B19 -> 1000 | C7: reinvested opex/capex | D7: ='3 Forecast'!C28 -> 20256 | E7: ='3 Forecast'!C31 -> 1.3559003 | F7: ='3 Forecast'!C30 -> 5.9610032 | G7: Near-term drag / higher growth option | H7: Top priority

Sheet 8 Accretion Dilution
A1: Basic Accretion / Dilution
A3: Acquisition case | B3: Value | D3: Capital return case | E3: Base | F3: Buyback | G3: Debt Reduction | H3: Investment Case
A4: Purchase price | B4: ='1 Inputs'!B14 -> 3000 | D4: Net income | E4: ='3 Forecast'!C11 -> 4194.2047 | F4: ='3 Forecast'!C11 -> 4194.2047 | G4: ='3 Forecast'!C11-B5*'1 Inputs'!B11*(1-'1 Inputs'!B12) -> 4194.1838 | H4: ='3 Forecast'!C11-250*(1-'1 Inputs'!B12) -> 3995.4547
A5: Cash % | B5: 0.5 | D5: Diluted shares | E5: ='3 Forecast'!B12 -> 968 | F5: ='3 Forecast'!C12 -> 860.9909 | G5: ='3 Forecast'!B12 -> 968 | H5: ='3 Forecast'!B12 -> 968
A6: Debt % | B6: 0.5 | D6: EPS | E6: =E4/E5 -> 4.3328561 | F6: =F4/F5 -> 4.8713694 | G6: =G4/G5 -> 4.3328346 | H6: =H4/H5 -> 4.1275359
A7: Target revenue | B7: ='1 Inputs'!B15 -> 800 | D7: EPS impact | F7: =F6/E6-1 -> 0.12428598 | G7: =G6/E6-1 -> -4.9756155e-06 | H7: =H6/E6-1 -> -0.047386814
A8: Target EBITDA | B8: =B7*'1 Inputs'!B16 -> 200 | D8: Strategic note | E8: No action | F8: Share count reduction | G8: Balance sheet protection | H8: Core growth investment
A9: Cost synergies | B9: ='1 Inputs'!B17 -> 75
A10: D&A / amortization | B10: 60
A11: Interest expense | B11: =B4*B6*'1 Inputs'!B11 -> 78.75
A12: Pre-tax contribution | B12: =B8+B9-B10 -> 215
A13: Tax expense | B13: =-B11*'1 Inputs'!B12 -> -16.14375
A14: Net income contribution | B14: =B11+B12 -> 293.75
A15: Base PYPL net income | B15: ='3 Forecast'!C11 -> 4194.2047
A16: PF net income | B16: =B13+B14 -> 277.60625
A17: EPS accretion / dilution | B17: =(B15/'3 Forecast'!C12)/'3 Forecast'!C13-1 -> 0

Sheet 9 Sensitivities
A1: Scenario and Sensitivity Tables
A3: 2030E EPS Sensitivity | B3: 16.0% | C3: 18.0% | D3: 20.0% | E3: 22.0% | F3: 24.0%
A4: 0.02 | B4: =('2 Historical FS'!F4*(1+A4)^5*0.16*(1-'1 Inputs'!$B$12))/800 -> 5.8233064 | C4: =('2 Historical FS'!F4*(1+A4)^5*0.18*(1-'1 Inputs'!$B$12))/800 -> 6.5512197 | D4: =('2 Historical FS'!F4*(1+A4)^5*0.2*(1-'1 Inputs'!$B$12))/800 -> 7.279133 | E4: =('2 Historical FS'!F4*(1+A4)^5*0.22*(1-'1 Inputs'!$B$12))/800 -> 8.0070463 | F4: =('2 Historical FS'!F4*(1+A4)^5*0.24*(1-'1 Inputs'!$B$12))/800 -> 8.7349596
A5: 0.04 | B5: =('2 Historical FS'!F4*(1+A5)^5*0.16*(1-'1 Inputs'!$B$12))/800 -> 6.4170508 | C5: =('2 Historical FS'!F4*(1+A5)^5*0.18*(1-'1 Inputs'!$B$12))/800 -> 7.2191822 | D5: =('2 Historical FS'!F4*(1+A5)^5*0.2*(1-'1 Inputs'!$B$12))/800 -> 8.0213135 | E5: =('2 Historical FS'!F4*(1+A5)^5*0.22*(1-'1 Inputs'!$B$12))/800 -> 8.8234449 | F5: =('2 Historical FS'!F4*(1+A5)^5*0.24*(1-'1 Inputs'!$B$12))/800 -> 9.6255762
A6: 0.06 | B6: =('2 Historical FS'!F4*(1+A6)^5*0.16*(1-'1 Inputs'!$B$12))/800 -> 7.0582674 | C6: =('2 Historical FS'!F4*(1+A6)^5*0.18*(1-'1 Inputs'!$B$12))/800 -> 7.9405508 | D6: =('2 Historical FS'!F4*(1+A6)^5*0.2*(1-'1 Inputs'!$B$12))/800 -> 8.8228342 | E6: =('2 Historical FS'!F4*(1+A6)^5*0.22*(1-'1 Inputs'!$B$12))/800 -> 9.7051177 | F6: =('2 Historical FS'!F4*(1+A6)^5*0.24*(1-'1 Inputs'!$B$12))/800 -> 10.587401
A7: 0.08 | B7: =('2 Historical FS'!F4*(1+A7)^5*0.16*(1-'1 Inputs'!$B$12))/800 -> 7.7497476 | C7: =('2 Historical FS'!F4*(1+A7)^5*0.18*(1-'1 Inputs'!$B$12))/800 -> 8.7184661 | D7: =('2 Historical FS'!F4*(1+A7)^5*0.2*(1-'1 Inputs'!$B$12))/800 -> 9.6871845 | E7: =('2 Historical FS'!F4*(1+A7)^5*0.22*(1-'1 Inputs'!$B$12))/800 -> 10.655903 | F7: =('2 Historical FS'!F4*(1+A7)^5*0.24*(1-'1 Inputs'!$B$12))/800 -> 11.624621
A8: 0.1 | B8: =('2 Historical FS'!F4*(1+A8)^5*0.16*(1-'1 Inputs'!$B$12))/800 -> 8.4943902 | C8: =('2 Historical FS'!F4*(1+A8)^5*0.18*(1-'1 Inputs'!$B$12))/800 -> 9.556189 | D8: =('2 Historical FS'!F4*(1+A8)^5*0.2*(1-'1 Inputs'!$B$12))/800 -> 10.617988 | E8: =('2 Historical FS'!F4*(1+A8)^5*0.22*(1-'1 Inputs'!$B$12))/800 -> 11.679787 | F8: =('2 Historical FS'!F4*(1+A8)^5*0.24*(1-'1 Inputs'!$B$12))/800 -> 12.741585
A11: Decision matrix | B11: Repurchase | C11: Debt reduction | D11: M&A | E11: Venmo + checkout
A12: Financial return | B12: 4 | C12: 2 | D12: 3 | E12: 4
A13: Strategic control | B13: 2 | C13: 1 | D13: 4 | E13: 5
A14: Execution complexity | B14: 1 | C14: 1 | D14: 5 | E14: 3
A15: Balance sheet risk | B15: 2 | C15: 1 | D15: 4 | E15: 2
A16: Multiple expansion potential | B16: 2 | C16: 1 | D16: 3 | E16: 5
A17: Weighted score | B17: =B12*25%+B13*25%-B14*20%-B15*15%+B16*15% -> 1.3 | C17: =C12*25%+C13*25%-C14*20%-C15*15%+C16*15% -> 0.55 | D17: =D12*25%+D13*25%-D14*20%-D15*15%+D16*15% -> 0.6 | E17: =E12*25%+E13*25%-E14*20%-E15*15%+E16*15% -> 2.1

Sheet 10 Recommendation
A1: Recommendation, Risks and Next Steps
A3: Priority | B3: Action | C3: Rationale
A4: 1 | B4: Invest in Venmo and branded checkout | C4: Best addresses growth, engagement and multiple expansion.
A5: 2 | B5: Continue valuation-sensitive repurchases | C5: FCF and low multiple support buybacks, but repurchases alone do not fix growth.
A6: 3 | B6: Selective debt reduction | C6: Manage maturities and preserve rating flexibility without over-allocating capital.
A7: 4 | B7: Small strategic tuck-ins only | C7: Avoid transformational M&A; pursue technology/product gaps with clear synergies.
A10: Risks | B10: Branded checkout competition; macro slowdown; regulatory pressure; execution risk; M&A integration risk
A11: Next steps | B11: Refresh with Q2 2026 results; improve peer data; diligence Venmo unit economics; update debt maturity profile
A12: Resume bullets | B12: Built integrated three-statement forecast, DCF, comps, precedent transactions, financing alternatives, accretion/dilution, and strategic pitch deck.

Sheet 11 Sources
A1: Source Register
A3: Source | B3: Type | C3: URL / File | D3: Used for | E3: Date accessed
A4: PayPal 2025 Form 10-K | B4: Company filing | C4: https://s205.q4cdn.com/875401827/files/doc_financials/2025/q4/10-K.pdf | D4: Historical financials, debt, buybacks | E4: 2026-07-28
A5: PayPal 1Q26 Earnings Release | B5: Company release | C5: https://s205.q4cdn.com/875401827/files/doc_financials/2026/q1/PYPL-1Q-26-Earnings-Release.pdf | D5: Latest quarter metrics, cash/debt, repurchases | E5: 2026-07-28
A6: PayPal 1Q26 Earnings Presentation | B6: Company presentation | C6: https://s205.q4cdn.com/875401827/files/doc_financials/2026/q1/PYPL-1Q-26-Earnings-Presentation.pdf | D6: Guidance, Venmo and branded checkout metrics | E6: 2026-07-28
A7: Market data snapshot | B7: Public market data | C7: Finance snapshot / Yahoo Finance / public sources | D7: Current price, market cap, peer multiples | E7: 2026-07-28
A8: Precedent announcements | B8: Company press releases | C8: PayPal-Honey; Visa-Pismo; Block-Afterpay; Fiserv-First Data; Global Payments-TSYS | D8: Transaction values and rationale | E8: 2026-07-28
A10: Important note | B10: This is an educational IB-style project. Several peer/transaction multiples are illustrative and should be updated with paid data sources before professional use.
A11: Files | B11: The resource folder contains downloaded company PDFs used to build the project.
